CanteenHRO
