Metadata-Version: 1.0
Name: CanteenHRO
Version: 0.0.3
Summary: Parses the menus of the canteens in Rostock.
Home-page: https://github.com/mperlet/CanteenHRO
Author: Mathias Perlet
Author-email: mathias@mperlet.de
License: UNKNOWN
Keywords: Rostock,Canteen,Mensa
Platform: UNKNOWN
